vampyre/__init__.py
vampyre/browser.py
vampyre/dogpile.py
vampyre/google.py
vampyre/simple_request.py
vampyre/util.py
vampyre/venere.py
vampyre/yboss.py
vampyre-0.0.3.dist-info/LICENSE
vampyre-0.0.3.dist-info/METADATA
vampyre-0.0.3.dist-info/WHEEL
vampyre-0.0.3.dist-info/top_level.txt
vampyre-0.0.3.dist-info/RECORD
