Metadata-Version: 2.1
Name: vampyre
Version: 0.0.3
Summary: Slurping tools
Home-page: https://github.com/thorwhalen/newut/tree/master/vampyre
Author: Thor Whalen
License: mit
Platform: any
License-File: LICENSE
